{
  "timestamp": "2025-11-05T00:29:56.393969",
  "dry_run": false,
  "options": {
    "dry_run": false,
    "redis_db": 1,
    "skip_neo4j": false,
    "skip_qdrant": false,
    "skip_redis": false,
    "report_dir": "reports/cleanup",
    "quiet": false,
    "restore_metadata": false
  },
  "before": {
    "neo4j": {
      "total_nodes": 6794,
      "total_relationships": 6589,
      "preserved_nodes": {
        "SchemaVersion": 1
      },
      "deletable_nodes": {
        "Step": 2337,
        "CitationUnit": 1556,
        "Configuration": 1125,
        "Section": 696,
        "Chunk": 696,
        "Procedure": 530,
        "Command": 286,
        "Document": 263
      },
      "constraints": 16,
      "indexes": 46
    },
    "qdrant": {
      "chunks": {
        "vector_count": 696,
        "config": "size=1024 distance=<Distance.COSINE: 'Cosine'> hnsw_config=None quantization_config=None on_disk=Non"
      },
      "CONFIGURATION": {
        "vector_count": 0,
        "config": "size=1024 distance=<Distance.COSINE: 'Cosine'> hnsw_config=None quantization_config=None on_disk=Non"
      },
      "curl": {
        "vector_count": 0,
        "config": "size=1024 distance=<Distance.COSINE: 'Cosine'> hnsw_config=None quantization_config=None on_disk=Non"
      },
      "Canonical": {
        "vector_count": 0,
        "config": "size=1024 distance=<Distance.COSINE: 'Cosine'> hnsw_config=None quantization_config=None on_disk=Non"
      },
      "logs": {
        "vector_count": 0,
        "config": "size=1024 distance=<Distance.COSINE: 'Cosine'> hnsw_config=None quantization_config=None on_disk=Non"
      },
      "configuration": {
        "vector_count": 0,
        "config": "size=1024 distance=<Distance.COSINE: 'Cosine'> hnsw_config=None quantization_config=None on_disk=Non"
      },
      "upsert": {
        "vector_count": 0,
        "config": "size=1024 distance=<Distance.COSINE: 'Cosine'> hnsw_config=None quantization_config=None on_disk=Non"
      },
      "See": {
        "vector_count": 0,
        "config": "size=1024 distance=<Distance.COSINE: 'Cosine'> hnsw_config=None quantization_config=None on_disk=Non"
      },
      "-": {
        "vector_count": 0,
        "config": "size=1024 distance=<Distance.COSINE: 'Cosine'> hnsw_config=None quantization_config=None on_disk=Non"
      },
      "stats": {
        "vector_count": 0,
        "config": "size=1024 distance=<Distance.COSINE: 'Cosine'> hnsw_config=None quantization_config=None on_disk=Non"
      },
      "Schema": {
        "vector_count": 0,
        "config": "size=1024 distance=<Distance.COSINE: 'Cosine'> hnsw_config=None quantization_config=None on_disk=Non"
      },
      "indexes": {
        "vector_count": 0,
        "config": "size=1024 distance=<Distance.COSINE: 'Cosine'> hnsw_config=None quantization_config=None on_disk=Non"
      },
      "points": {
        "vector_count": 0,
        "config": "size=1024 distance=<Distance.COSINE: 'Cosine'> hnsw_config=None quantization_config=None on_disk=Non"
      },
      "Setup": {
        "vector_count": 0,
        "config": "size=1024 distance=<Distance.COSINE: 'Cosine'> hnsw_config=None quantization_config=None on_disk=Non"
      },
      "with": {
        "vector_count": 0,
        "config": "size=1024 distance=<Distance.COSINE: 'Cosine'> hnsw_config=None quantization_config=None on_disk=Non"
      },
      "already": {
        "vector_count": 0,
        "config": "size=1024 distance=<Distance.COSINE: 'Cosine'> hnsw_config=None quantization_config=None on_disk=Non"
      },
      "collection": {
        "vector_count": 0,
        "config": "size=1024 distance=<Distance.COSINE: 'Cosine'> hnsw_config=None quantization_config=None on_disk=Non"
      },
      "sections": {
        "vector_count": 0,
        "config": "size=1024 distance=<Distance.COSINE: 'Cosine'> hnsw_config=None quantization_config=None on_disk=Non"
      },
      "string": {
        "vector_count": 0,
        "config": "size=1024 distance=<Distance.COSINE: 'Cosine'> hnsw_config=None quantization_config=None on_disk=Non"
      },
      "Section": {
        "vector_count": 0,
        "config": "size=1024 distance=<Distance.COSINE: 'Cosine'> hnsw_config=None quantization_config=None on_disk=Non"
      }
    },
    "redis": {
      "db": 1,
      "total_keys": 0,
      "system_keys": 0,
      "data_keys": 0,
      "sample_data_keys": [],
      "preserved_keys": []
    }
  },
  "after": {
    "neo4j": {
      "total_nodes": 1,
      "total_relationships": 0,
      "preserved_nodes": {
        "SchemaVersion": 1
      },
      "constraints": 16,
      "indexes": 46
    },
    "qdrant": {
      "chunks": {
        "vector_count": 0,
        "preserved": true
      },
      "CONFIGURATION": {
        "vector_count": 0,
        "preserved": true
      },
      "curl": {
        "vector_count": 0,
        "preserved": true
      },
      "Canonical": {
        "vector_count": 0,
        "preserved": true
      },
      "logs": {
        "vector_count": 0,
        "preserved": true
      },
      "configuration": {
        "vector_count": 0,
        "preserved": true
      },
      "upsert": {
        "vector_count": 0,
        "preserved": true
      },
      "See": {
        "vector_count": 0,
        "preserved": true
      },
      "-": {
        "vector_count": 0,
        "preserved": true
      },
      "stats": {
        "vector_count": 0,
        "preserved": true
      },
      "Schema": {
        "vector_count": 0,
        "preserved": true
      },
      "indexes": {
        "vector_count": 0,
        "preserved": true
      },
      "points": {
        "vector_count": 0,
        "preserved": true
      },
      "Setup": {
        "vector_count": 0,
        "preserved": true
      },
      "with": {
        "vector_count": 0,
        "preserved": true
      },
      "already": {
        "vector_count": 0,
        "preserved": true
      },
      "collection": {
        "vector_count": 0,
        "preserved": true
      },
      "sections": {
        "vector_count": 0,
        "preserved": true
      },
      "string": {
        "vector_count": 0,
        "preserved": true
      },
      "Section": {
        "vector_count": 0,
        "preserved": true
      }
    },
    "redis": {
      "db": 1,
      "total_keys": 0,
      "preserved_keys": 0
    }
  },
  "actions": [
    {
      "timestamp": "2025-11-05T00:29:57.048813",
      "action": "neo4j_selective_delete",
      "details": {
        "nodes_deleted": 6793,
        "labels_deleted": [
          "Step",
          "CitationUnit",
          "Configuration",
          "Section",
          "Chunk",
          "Procedure",
          "Command",
          "Document"
        ],
        "preserved_labels": [
          "SchemaVersion"
        ]
      }
    },
    {
      "timestamp": "2025-11-05T00:29:57.232132",
      "action": "qdrant_delete_points",
      "details": {
        "collection": "chunks",
        "vectors_deleted": 696
      }
    }
  ],
  "errors": [],
  "summary": {
    "dry_run": false,
    "success": true,
    "metadata_preserved": true,
    "databases_cleaned": [
      {
        "database": "neo4j",
        "data_nodes_deleted": 7489,
        "metadata_nodes_preserved": 1,
        "schema_preserved": true
      },
      {
        "database": "qdrant",
        "collections_preserved": 20,
        "total_vectors_deleted": 696
      },
      {
        "database": "redis",
        "db": 1,
        "data_keys_deleted": 0,
        "system_keys_preserved": 0
      }
    ]
  },
  "preserved_nodes": []
}
